llm_insight_forge/__init__.py
llm_insight_forge/cli.py
llm_insight_forge/evaluation/__init__.py
llm_insight_forge/evaluation/benchmarks.py
llm_insight_forge/evaluation/evaluator.py
llm_insight_forge/evaluation/metrics.py
llm_insight_forge/fine_tuning/__init__.py
llm_insight_forge/fine_tuning/dataset_preparation.py
llm_insight_forge/fine_tuning/parameter_efficient.py
llm_insight_forge/fine_tuning/sft.py
llm_insight_forge/fine_tuning/trainer.py
llm_insight_forge/inference_optimization/__init__.py
llm_insight_forge/inference_optimization/quantization.py
llm_insight_forge/prompt_engineering/__init__.py
llm_insight_forge/prompt_engineering/jailbreak_detector.py
llm_insight_forge/prompt_engineering/optimizer.py
llm_insight_forge/prompt_engineering/template.py
llm_insight_forge/utils/__init__.py
llm_insight_forge-0.1.2.dist-info/licenses/LICENSE
llm_insight_forge-0.1.2.dist-info/METADATA
llm_insight_forge-0.1.2.dist-info/WHEEL
llm_insight_forge-0.1.2.dist-info/top_level.txt
llm_insight_forge-0.1.2.dist-info/RECORD
