Metadata-Version: 2.4
Name: llm_insight_forge
Version: 0.1.2
Summary: A comprehensive toolkit for LLM evaluation, prompt engineering, fine-tuning, and inference optimization
Home-page: https://github.com/biswanathroul/llm_insight_forge
Author: Biswanath Roul
License: MIT
Project-URL: Homepage, https://github.com/biswanathroul/llm_insight_forge
Project-URL: Bug Tracker, https://github.com/biswanathroul/llm_insight_forge/issues
Project-URL: Documentation, https://llm-insight-forge.readthedocs.io/
Keywords: llm,nlp,evaluation,prompt-engineering,fine-tuning,quantization
Classifier: Programming Language :: Python :: 3
Classifier: Programming Language :: Python :: 3.8
Classifier: Programming Language :: Python :: 3.9
Classifier: Programming Language :: Python :: 3.10
Classifier: Programming Language :: Python :: 3.11
Classifier: License :: OSI Approved :: MIT License
Classifier: Operating System :: OS Independent
Classifier: Topic :: Scientific/Engineering :: Artificial Intelligence
Classifier: Intended Audience :: Developers
Classifier: Intended Audience :: Science/Research
Requires-Python: >=3.8
License-File: LICENSE
Requires-Dist: torch>=1.10.0
Requires-Dist: transformers>=4.20.0
Requires-Dist: numpy>=1.19.0
Requires-Dist: scikit-learn>=1.0.0
Requires-Dist: nltk>=3.6.0
Requires-Dist: rouge-score>=0.1.0
Requires-Dist: datasets>=2.0.0
Requires-Dist: tqdm>=4.62.0
Provides-Extra: fine-tuning
Requires-Dist: peft>=0.4.0; extra == "fine-tuning"
Requires-Dist: accelerate>=0.20.0; extra == "fine-tuning"
Requires-Dist: bitsandbytes>=0.40.0; extra == "fine-tuning"
Provides-Extra: quantization
Requires-Dist: bitsandbytes>=0.40.0; extra == "quantization"
Requires-Dist: optimum>=1.8.0; extra == "quantization"
Provides-Extra: dev
Requires-Dist: pytest>=7.0.0; extra == "dev"
Requires-Dist: pytest-cov>=3.0.0; extra == "dev"
Requires-Dist: black>=22.0.0; extra == "dev"
Requires-Dist: isort>=5.10.0; extra == "dev"
Requires-Dist: flake8>=4.0.0; extra == "dev"
Requires-Dist: mypy>=0.940; extra == "dev"
Provides-Extra: docs
Requires-Dist: sphinx>=4.4.0; extra == "docs"
Requires-Dist: sphinx-rtd-theme>=1.0.0; extra == "docs"
Requires-Dist: myst-parser>=0.18.0; extra == "docs"
Provides-Extra: all
Requires-Dist: peft>=0.4.0; extra == "all"
Requires-Dist: accelerate>=0.20.0; extra == "all"
Requires-Dist: bitsandbytes>=0.40.0; extra == "all"
Requires-Dist: optimum>=1.8.0; extra == "all"
Dynamic: home-page
Dynamic: license-file
Dynamic: requires-python
